enchant/__init__.py
enchant/_enchant.py
enchant/errors.py
enchant/pypwl.py
enchant/utils.py
enchant/checker/CmdLineChecker.py
enchant/checker/GtkSpellCheckerDialog.py
enchant/checker/__init__.py
enchant/checker/wxSpellCheckerDialog.py
enchant/tokenize/__init__.py
enchant/tokenize/en.py
pyenchant-3.2.1.dist-info/LICENSE.txt
pyenchant-3.2.1.dist-info/METADATA
pyenchant-3.2.1.dist-info/WHEEL
pyenchant-3.2.1.dist-info/top_level.txt
pyenchant-3.2.1.dist-info/RECORD
